{"response": {"header": {"resultCode": "00", "resultMsg": "NORMAL SERVICE."}, "body": {"numOfRows": 1000, "pageNo": 1, "totalCount": 232, "items": {"item": [{"basDt": "20250224", "idxNm": "10\ub144\uad6d\ucc44\uc120\ubb3c \ub808\ubc84\ub9ac\uc9c0\uc9c0\uc218", "clpr": "2026.13", "vs": "9.99", "fltRt": ".5", "mkp": "2024.78", "hipr": "2031.25", "lopr": "2024.78", "trqu": "0", "trPrc": "0"}, {"basDt": "20250224", "idxNm": "10\ub144\uad6d\ucc44\uc120\ubb3c \uc778\ubc84\uc2a4 \ub808\ubc84\ub9ac\uc9c0\uc9c0\uc218", "clpr": "765.86", "vs": "-3.47", "fltRt": "-.45", "mkp": "766.38", "hipr": "766.38", "lopr": "763.91", "trqu": "0", "trPrc": "0"}, {"basDt": "20250224", "idxNm": "10\ub144\uad6d\ucc44\uc120\ubb3c \uc778\ubc84\uc2a4\uc9c0\uc218", "clpr": "1153.2", "vs": "-2.47", "fltRt": "-.21", "mkp": "1153.59", "hipr": "1153.59", "lopr": "1151.73", "trqu": "0", "trPrc": "0"}, {"basDt": "20250224", "idxNm": "10\ub144\uad6d\ucc44\uc120\ubb3c\uc9c0\uc218", "clpr": "1249.26", "vs": "2.95", "fltRt": ".24", "mkp": "1248.84", "hipr": "1250.84", "lopr": "1248.84", "trqu": "0", "trPrc": "0"}, {"basDt": "20250224", "idxNm": "5\ub144 \uad6d\ucc44\uc120\ubb3c \ucd94\uc885 \uc778\ubc84\uc2a4\uc9c0\uc218", "clpr": "1180.23", "vs": "-.72", "fltRt": "-.06", "mkp": "1180.04", "hipr": "1180.39", "lopr": "1179.43", "trqu": "0", "trPrc": "0"}, {"basDt": "20250224", "idxNm": "5\ub144 \uad6d\ucc44\uc120\ubb3c \ucd94\uc885 \uc9c0\uc218", "clpr": "1023.13", "vs": ".86", "fltRt": ".08", "mkp": "1023.3", "hipr": "1023.82", "lopr": "1022.99", "trqu": "0", "trPrc": "0"}, {"basDt": "20250224", "idxNm": "KRX 100 \ub3d9\uc77c\uac00\uc911\uc9c0\uc218", "clpr": "2113.98", "vs": "-1.62", "fltRt": "-.08", "mkp": "2102.02", "hipr": "2114.05", "lopr": "2096.15", "trqu": "166680532", "trPrc": "8172194333742"}, {"basDt": "20250224", "idxNm": "KRX 2\ucc28\uc804\uc9c0 TOP 10 \ub808\ubc84\ub9ac\uc9c0\uc9c0\uc218", "clpr": "2806.2", "vs": "122.92", "fltRt": "4.58", "mkp": "2630.42", "hipr": "2821.53", "lopr": "2626.06", "trqu": "0", "trPrc": "0"}, {"basDt": "20250224", "idxNm": "KRX 2\ucc28\uc804\uc9c0 TOP 10 \uc120\ubb3c TWAP \uc778\ubc84\uc2a4\uc9c0\uc218", "clpr": "1438.41", "vs": "-44.67", "fltRt": "-3.01", "mkp": "1483.37", "hipr": "1490.21", "lopr": "1438.41", "trqu": "0", "trPrc": "0"}, {"basDt": "20250224", "idxNm": "KRX 2\ucc28\uc804\uc9c0 TOP 10 \uc120\ubb3c TWAP \uc9c0\uc218", "clpr": "458.41", "vs": "13.49", "fltRt": "3.03", "mkp": "444.92", "hipr": "458.41", "lopr": "442.87", "trqu": "0", "trPrc": "0"}, {"basDt": "20250224", "idxNm": "KRX 2\ucc28\uc804\uc9c0 TOP 10 \uc8fc\uc2dd\uad6d\ucc44\ud63c\ud569(\ucc44\uad8c\ud615)\uc9c0\uc218", "clpr": "1845.06", "vs": "13.1", "fltRt": ".72", "mkp": "1826.87", "hipr": "1846.85", "lopr": "1826.32", "trqu": "0", "trPrc": "0"}, {"basDt": "20250224", "idxNm": "KRX 300 TR", "clpr": "2073.46", "vs": "-10.71", "fltRt": "-.51", "mkp": "2065.89", "hipr": "2073.46", "lopr": "2057.26", "trqu": "0", "trPrc": "0"}, {"basDt": "20250224", "idxNm": "KRX 300 \ub808\ubc84\ub9ac\uc9c0\uc9c0\uc218", "clpr": "820.29", "vs": "-8.72", "fltRt": "-1.05", "mkp": "814.28", "hipr": "820.29", "lopr": "807.41", "trqu": "0", "trPrc": "0"}, {"basDt": "20250224", "idxNm": "KRX 300 \ubbf8\uad6d\ub2ec\ub7ec \uc120\ubb3c\ud63c\ud569\uc9c0\uc218", "clpr": "1752.34", "vs": "-19.47", "fltRt": "-1.1", "mkp": "1772.17", "hipr": "1776.25", "lopr": "1744.5", "trqu": "0", "trPrc": "0"}, {"basDt": "20250224", "idxNm": "KRX 300 \uc120\ubb3c \ub808\ubc84\ub9ac\uc9c0\uc9c0\uc218(F-KRX 300 Leverage)", "clpr": "892.7", "vs": "-10.72", "fltRt": "-1.19", "mkp": "903.59", "hipr": "903.59", "lopr": "882.94", "trqu": "0", "trPrc": "0"}, {"basDt": "20250224", "idxNm": "KRX 300 \uc120\ubb3c \uc778\ubc84\uc2a4-2X\uc9c0\uc218(F-KRX 300 Inverse-2X)", "clpr": "496.26", "vs": "6.01", "fltRt": "1.23", "mkp": "490.34", "hipr": "501.55", "lopr": "490.34", "trqu": "0", "trPrc": "0"}, {"basDt": "20250224", "idxNm": "KRX 300 \uc120\ubb3c \uc778\ubc84\uc2a4\uc9c0\uc218", "clpr": "866.57", "vs": "5.38", "fltRt": ".62", "mkp": "861.37", "hipr": "871.22", "lopr": "861.37", "trqu": "0", "trPrc": "0"}, {"basDt": "20250224", "idxNm": "KRX 300 \uc120\ubb3c\uc9c0\uc218", "clpr": "1015.54", "vs": "-6.16", "fltRt": "-.6", "mkp": "1021.7", "hipr": "1021.7", "lopr": "1010.02", "trqu": "0", "trPrc": "0"}, {"basDt": "20250224", "idxNm": "KRX BBIG \ub808\ubc84\ub9ac\uc9c0\uc9c0\uc218", "clpr": "1550.77", "vs": "-17.36", "fltRt": "-1.11", "mkp": "1532.77", "hipr": "1554.14", "lopr": "1530.35", "trqu": "0", "trPrc": "0"}, {"basDt": "20250224", "idxNm": "KRX BBIG \ub9ac\uc2a4\ud06c\ucee8\ud2b8\ub864 12% \ube44\uc6a9 \ucc28\uac10\ud615 \uc9c0\uc218", "clpr": "986.89", "vs": "-3.09", "fltRt": "-.31", "mkp": "984.49", "hipr": "987.46", "lopr": "983.33", "trqu": "0", "trPrc": "0"}, {"basDt": "20250224", "idxNm": "KRX BBIG \ub9ac\uc2a4\ud06c\ucee8\ud2b8\ub864 12% \uc9c0\uc218", "clpr": "1333.57", "vs": "-3.87", "fltRt": "-.29", "mkp": "1330.32", "hipr": "1334.33", "lopr": "1328.76", "trqu": "0", "trPrc": "0"}, {"basDt": "20250224", "idxNm": "KRX BBIG \uc8fc\uc2dd\uad6d\ucc44\ud63c\ud569(\ucc44\uad8c\ud615)\uc9c0\uc218", "clpr": "1448.43", "vs": "-2", "fltRt": "-.14", "mkp": "1446.28", "hipr": "1449.11", "lopr": "1445.65", "trqu": "0", "trPrc": "0"}, {"basDt": "20250224", "idxNm": "KRX Bloomberg \ucf54\uc2a4\ud53c 200 \ub2e4\uc774\ub098\ubbf9 \uc704\ud074\ub9ac \ucee4\ubc84\ub4dc\ucf5c \uc9c0\uc218", "clpr": "1384.83", "vs": "-4.61", "fltRt": "-.33", "mkp": "1392.68", "hipr": "1392.68", "lopr": "1375", "trqu": "0", "trPrc": "0"}, {"basDt": "20250224", "idxNm": "KRX Bloomberg \ucf54\uc2a4\ud53c 200 \ubca0\uc5b4 \ucc44\uad8c \ud63c\ud569\uc9c0\uc218", "clpr": "923.98", "vs": "3.74", "fltRt": ".41", "mkp": "924.35", "hipr": "925.5", "lopr": "923.09", "trqu": "0", "trPrc": "0"}, {"basDt": "20250224", "idxNm": "KRX Bloomberg \ucf54\uc2a4\ud53c 200 \uc2a4\ub9c8\ud2b8 \ud06c\ub8e8\uc988 \uc9c0\uc218", "clpr": "1582.84", "vs": "-9.14", "fltRt": "-.57", "mkp": "1578.68", "hipr": "1582.84", "lopr": "1571.58", "trqu": "0", "trPrc": "0"}, {"basDt": "20250224", "idxNm": "KRX Cboe \ucf54\uc2a4\ud53c 200 \ucf5c\ub9e4\ub3c4 \uc9c0\uc218", "clpr": "185.37", "vs": ".02", "fltRt": ".01", "mkp": "186.55", "hipr": "186.67", "lopr": "184.47", "trqu": "0", "trPrc": "0"}, {"basDt": "20250224", "idxNm": "KRX Cboe \ucf54\uc2a4\ud53c 200 \ud48b\ub9e4\ub3c4 \uc9c0\uc218", "clpr": "223.89", "vs": "-.69", "fltRt": "-.31", "mkp": "223.65", "hipr": "224.09", "lopr": "223.37", "trqu": "0", "trPrc": "0"}, {"basDt": "20250224", "idxNm": "KRX \uae08\ud604\ubb3c \ub808\ubc84\ub9ac\uc9c0 \uc9c0\uc218", "clpr": "8033.46", "vs": "-71.68", "fltRt": "-.88", "mkp": "8179.44", "hipr": "8327.63", "lopr": "7908.48", "trqu": "0", "trPrc": "0"}, {"basDt": "20250224", "idxNm": "KRX \uae08\ud604\ubb3c\uc9c0\uc218", "clpr": "3422.13", "vs": "-14.79", "fltRt": "-.43", "mkp": "3453.08", "hipr": "3484.5", "lopr": "3395.63", "trqu": "394950", "trPrc": "57859720810"}, {"basDt": "20250224", "idxNm": "KRX \uae08\ud604\ubb3c\uc9c0\uc218 USD", "clpr": "2645.5", "vs": "1.25", "fltRt": ".05", "mkp": "2656.68", "hipr": "2680.13", "lopr": "2620.15", "trqu": "394950", "trPrc": "40539303"}, {"basDt": "20250224", "idxNm": "KRX \ub098\uc2a4\ub2e5 100 ETF \uc120\ubb3c \ub808\ubc84\ub9ac\uc9c0 \uc9c0\uc218", "clpr": "2678.51", "vs": "-137.05", "fltRt": "-4.87", "mkp": "2816.08", "hipr": "2816.08", "lopr": "2676.33", "trqu": "0", "trPrc": "0"}, {"basDt": "20250224", "idxNm": "KRX \ub098\uc2a4\ub2e5 100 ETF \uc120\ubb3c \uc778\ubc84\uc2a4 \uc9c0\uc218", "clpr": "565.72", "vs": "13.6", "fltRt": "2.46", "mkp": "552.24", "hipr": "565.94", "lopr": "552.24", "trqu": "0", "trPrc": "0"}, {"basDt": "20250224", "idxNm": "KRX \ub098\uc2a4\ub2e5 100 ETF \uc120\ubb3c\uc9c0\uc218", "clpr": "1685.98", "vs": "-42.22", "fltRt": "-2.44", "mkp": "1728.2", "hipr": "1728.2", "lopr": "1685.31", "trqu": "0", "trPrc": "0"}, {"basDt": "20250224", "idxNm": "KRX \ub098\uc2a4\ub2e5 100 ETF \uc778\ubc84\uc2a4 -2X \uc9c0\uc218", "clpr": "249.47", "vs": "11.66", "fltRt": "4.9", "mkp": "237.85", "hipr": "249.66", "lopr": "237.85", "trqu": "0", "trPrc": "0"}, {"basDt": "20250224", "idxNm": "KRX \ub2e4\uc6b0\uc874\uc2a4 \ubbf8\uad6d\ubc30\ub2f9\uad6d\ucc44 \ud63c\ud569\uc9c0\uc218", "clpr": "1287.09", "vs": ".09", "fltRt": ".01", "mkp": "0", "hipr": "0", "lopr": "0", "trqu": "0", "trPrc": null}, {"basDt": "20250224", "idxNm": "KRX \ub9ac\uce20 TOP 10 \ub808\ubc84\ub9ac\uc9c0 \uc9c0\uc218", "clpr": "499.88", "vs": "4.15", "fltRt": ".84", "mkp": "496.18", "hipr": "505.22", "lopr": "494.06", "trqu": "0", "trPrc": "0"}, {"basDt": "20250224", "idxNm": "KRX \ubc18\ub3c4\uccb4 TR \ub808\ubc84\ub9ac\uc9c0 \uc9c0\uc218", "clpr": "2354.35", "vs": "-103.85", "fltRt": "-4.22", "mkp": "2350.12", "hipr": "2354.35", "lopr": "2283.01", "trqu": "0", "trPrc": "0"}, {"basDt": "20250224", "idxNm": "KRX \ubc18\ub3c4\uccb4 TR \uc9c0\uc218", "clpr": "4062.28", "vs": "-87.16", "fltRt": "-2.1", "mkp": "4058.71", "hipr": "4062.28", "lopr": "4002.07", "trqu": "0", "trPrc": "0"}, {"basDt": "20250224", "idxNm": "KRX \ubc18\ub3c4\uccb4 Top 15 TR \uc9c0\uc218", "clpr": "2716.71", "vs": "-60.92", "fltRt": "-2.19", "mkp": "2720.09", "hipr": "2721.35", "lopr": "2679.15", "trqu": "0", "trPrc": "0"}, {"basDt": "20250224", "idxNm": "KRX \ubc18\ub3c4\uccb4 \ub808\ubc84\ub9ac\uc9c0 \uc9c0\uc218", "clpr": "3959.42", "vs": "-174.64", "fltRt": "-4.22", "mkp": "3952.3", "hipr": "3959.42", "lopr": "3839.44", "trqu": "0", "trPrc": "0"}, {"basDt": "20250224", "idxNm": "KRX \ube14\ub8e8\uce69 25 TR \uc9c0\uc218", "clpr": "1917.03", "vs": "-12.57", "fltRt": "-.65", "mkp": "1909.36", "hipr": "1917.03", "lopr": "1903.01", "trqu": "0", "trPrc": "0"}, {"basDt": "20250224", "idxNm": "KRX \uc804\uae30\ucc28 Top 15 TR \uc9c0\uc218", "clpr": "2635.58", "vs": "37.51", "fltRt": "1.44", "mkp": "2572.8", "hipr": "2637.88", "lopr": "2571.39", "trqu": "0", "trPrc": "0"}, {"basDt": "20250224", "idxNm": "KRX \ucd5c\uc18c\ubcc0\ub3d9\uc131\uc9c0\uc218", "clpr": "6308.16", "vs": "-14.28", "fltRt": "-.23", "mkp": "6275.58", "hipr": "6308.16", "lopr": "6264.14", "trqu": "64167744", "trPrc": "3016513865700"}, {"basDt": "20250224", "idxNm": "KTOP 30 \ub808\ubc84\ub9ac\uc9c0\uc9c0\uc218", "clpr": "6653.08", "vs": "-19.01", "fltRt": "-.28", "mkp": "6590.2", "hipr": "6661.93", "lopr": "6563.25", "trqu": "0", "trPrc": "0"}, {"basDt": "20250224", "idxNm": "\uacbd\uae30\ubc29\uc5b4\uc18c\ube44\uc7ac \ucc44\uad8c\ud63c\ud569\uc9c0\uc218", "clpr": "1506.53", "vs": "-.11", "fltRt": "-.01", "mkp": "1505.75", "hipr": "1507.59", "lopr": "1504.5", "trqu": "0", "trPrc": "0"}, {"basDt": "20250224", "idxNm": "\uad6d\ucc44 3-10\ub144 \uc120\ubb3c \ub808\ubc84\ub9ac\uc9c0 \uc9c0\uc218", "clpr": "1307.45", "vs": "3.64", "fltRt": ".28", "mkp": "1307.49", "hipr": "1309.58", "lopr": "1307", "trqu": "0", "trPrc": "0"}, {"basDt": "20250224", "idxNm": "\uad6d\ucc44 3-10\ub144 \uc120\ubb3c \uc778\ubc84\uc2a4 \uc9c0\uc218", "clpr": "1500.26", "vs": "-1.57", "fltRt": "-.1", "mkp": "1500.23", "hipr": "1500.51", "lopr": "1499.03", "trqu": "0", "trPrc": "0"}, {"basDt": "20250224", "idxNm": "\uad6d\ucc44 3-10\ub144 \uc120\ubb3c \uc778\ubc84\uc2a4-2X\uc9c0\uc218", "clpr": "1519.39", "vs": "-3.55", "fltRt": "-.23", "mkp": "1519.34", "hipr": "1519.91", "lopr": "1516.89", "trqu": "0", "trPrc": "0"}, {"basDt": "20250224", "idxNm": "\uad6d\ucc44 3-10\ub144 \uc120\ubb3c\uc9c0\uc218", "clpr": "1173.38", "vs": "1.5", "fltRt": ".13", "mkp": "1173.4", "hipr": "1174.34", "lopr": "1173.18", "trqu": "0", "trPrc": "0"}, {"basDt": "20250224", "idxNm": "\uad6d\ucc44\uc120\ubb3c 3\ub144/10\ub144 \uc77c\ub4dc\ucee4\ube0c \uc2a4\ud2f0\ud504\ub2dd 2X \uc9c0\uc218", "clpr": "1394.55", "vs": "-1.37", "fltRt": "-.1", "mkp": "1395.93", "hipr": "1396.02", "lopr": "1394.03", "trqu": "0", "trPrc": "0"}, {"basDt": "20250224", "idxNm": "\uad6d\ucc44\uc120\ubb3c 3\ub144/10\ub144 \uc77c\ub4dc\ucee4\ube0c \uc2a4\ud2f0\ud504\ub2dd \uc9c0\uc218", "clpr": "1386.47", "vs": "-.51", "fltRt": "-.04", "mkp": "1387.15", "hipr": "1387.2", "lopr": "1386.21", "trqu": "0", "trPrc": "0"}, {"basDt": "20250224", "idxNm": "\uad6d\ucc44\uc120\ubb3c 3\ub144/10\ub144 \uc77c\ub4dc\ucee4\ube0c \ud50c\ub798\ud2b8\ub2dd 2X \uc9c0\uc218", "clpr": "1322.28", "vs": "1.9", "fltRt": ".14", "mkp": "1320.98", "hipr": "1322.77", "lopr": "1320.89", "trqu": "0", "trPrc": "0"}, {"basDt": "20250224", "idxNm": "\uad6d\ucc44\uc120\ubb3c 3\ub144/10\ub144 \uc77c\ub4dc\ucee4\ube0c \ud50c\ub798\ud2b8\ub2dd \uc9c0\uc218", "clpr": "1350.06", "vs": "1.13", "fltRt": ".08", "mkp": "1349.4", "hipr": "1350.31", "lopr": "1349.35", "trqu": "0", "trPrc": "0"}, {"basDt": "20250224", "idxNm": "\uad6d\ucc44\uc120\ubb3c \uc778\ubc84\uc2a4\uc9c0\uc218", "clpr": "1410.69", "vs": ".07", "fltRt": "0", "mkp": "1410.16", "hipr": "1410.82", "lopr": "1409.9", "trqu": "0", "trPrc": "0"}, {"basDt": "20250224", "idxNm": "\uad6d\ucc44\uc120\ubb3c\uc9c0\uc218", "clpr": "1238.13", "vs": ".23", "fltRt": ".02", "mkp": "1238.6", "hipr": "1238.83", "lopr": "1238.02", "trqu": "0", "trPrc": "0"}, {"basDt": "20250224", "idxNm": "\ubbf8\uad6d\ub2ec\ub7ec\uc120\ubb3c TR \uc9c0\uc218", "clpr": "1857.65", "vs": "-9.22", "fltRt": "-.49", "mkp": "1870.42", "hipr": "1870.95", "lopr": "1853.75", "trqu": "0", "trPrc": "0"}, {"basDt": "20250224", "idxNm": "\ubbf8\uad6d\ub2ec\ub7ec\uc120\ubb3c \ub808\ubc84\ub9ac\uc9c0\uc9c0\uc218", "clpr": "1706.7", "vs": "-18.22", "fltRt": "-1.06", "mkp": "1730.3", "hipr": "1731.27", "lopr": "1699.48", "trqu": "0", "trPrc": "0"}, {"basDt": "20250224", "idxNm": "\ubbf8\uad6d\ub2ec\ub7ec\uc120\ubb3c \uc778\ubc84\uc2a4-2X\uc9c0\uc218", "clpr": "505.42", "vs": "5.16", "fltRt": "1.03", "mkp": "498.58", "hipr": "507.52", "lopr": "498.3", "trqu": "0", "trPrc": "0"}, {"basDt": "20250224", "idxNm": "\ubbf8\uad6d\ub2ec\ub7ec\uc120\ubb3c \uc778\ubc84\uc2a4-3X\uc9c0\uc218", "clpr": "300.74", "vs": "4.59", "fltRt": "1.55", "mkp": "294.66", "hipr": "302.6", "lopr": "294.41", "trqu": "0", "trPrc": "0"}, {"basDt": "20250224", "idxNm": "\ubbf8\uad6d\ub2ec\ub7ec\uc120\ubb3c \uc778\ubc84\uc2a4\uc9c0\uc218", "clpr": "1156.44", "vs": "6.2", "fltRt": ".54", "mkp": "1148.57", "hipr": "1158.85", "lopr": "1148.25", "trqu": "0", "trPrc": "0"}, {"basDt": "20250224", "idxNm": "\ubbf8\uad6d\ub2ec\ub7ec\uc120\ubb3c\uc9c0\uc218", "clpr": "1559.12", "vs": "-8.09", "fltRt": "-.52", "mkp": "1569.84", "hipr": "1570.28", "lopr": "1555.84", "trqu": "0", "trPrc": "0"}, {"basDt": "20250224", "idxNm": "\ubbf8\ub2c8 \ucf54\uc2a4\ud53c 200 \uc120\ubb3c \ub808\ubc84\ub9ac\uc9c0\uc9c0\uc218", "clpr": "1792.53", "vs": "-35.28", "fltRt": "-1.93", "mkp": "1788.99", "hipr": "1801.29", "lopr": "1777.54", "trqu": "0", "trPrc": "0"}, {"basDt": "20250224", "idxNm": "\ubbf8\ub2c8 \ucf54\uc2a4\ud53c 200 \uc120\ubb3c \uc778\ubc84\uc2a4 \uc9c0\uc218", "clpr": "597.35", "vs": "5.89", "fltRt": "1", "mkp": "597.92", "hipr": "599.78", "lopr": "595.93", "trqu": "0", "trPrc": "0"}, {"basDt": "20250224", "idxNm": "\ubbf8\ub2c8 \ucf54\uc2a4\ud53c 200 \uc120\ubb3c \uc778\ubc84\uc2a4-2X\uc9c0\uc218", "clpr": "214.68", "vs": "4.14", "fltRt": "1.97", "mkp": "215.09", "hipr": "216.41", "lopr": "213.67", "trqu": "0", "trPrc": "0"}, {"basDt": "20250224", "idxNm": "\ubbf8\ub2c8 \ucf54\uc2a4\ud53c 200 \uc120\ubb3c\uc9c0\uc218", "clpr": "1451.09", "vs": "-14.28", "fltRt": "-.97", "mkp": "1449.67", "hipr": "1454.6", "lopr": "1445.08", "trqu": "0", "trPrc": "0"}, {"basDt": "20250224", "idxNm": "\ubc30\ub2f9\uc131\uc7a5 \ucc44\uad8c\ud63c\ud569\uc9c0\uc218", "clpr": "2071.58", "vs": "4.2", "fltRt": ".2", "mkp": "2064.98", "hipr": "2071.58", "lopr": "2064.59", "trqu": "0", "trPrc": "0"}, {"basDt": "20250224", "idxNm": "\uc5d4\uc120\ubb3c \ub808\ubc84\ub9ac\uc9c0\uc9c0\uc218", "clpr": "309.09", "vs": "1.23", "fltRt": ".4", "mkp": "311.08", "hipr": "313.86", "lopr": "308.63", "trqu": "0", "trPrc": "0"}, {"basDt": "20250224", "idxNm": "\uc5d4\uc120\ubb3c \uc778\ubc84\uc2a4-2X\uc9c0\uc218", "clpr": "665.22", "vs": "-2.82", "fltRt": "-.42", "mkp": "660.89", "hipr": "666.21", "lopr": "654.86", "trqu": "0", "trPrc": "0"}, {"basDt": "20250224", "idxNm": "\uc5d4\uc120\ubb3c \uc778\ubc84\uc2a4-3X\uc9c0\uc218", "clpr": "591.09", "vs": "-3.76", "fltRt": "-.63", "mkp": "585.3", "hipr": "592.4", "lopr": "577.25", "trqu": "0", "trPrc": "0"}, {"basDt": "20250224", "idxNm": "\uc5d4\uc120\ubb3c \uc778\ubc84\uc2a4\uc9c0\uc218", "clpr": "804.75", "vs": "-1.52", "fltRt": "-.19", "mkp": "802.14", "hipr": "805.34", "lopr": "798.5", "trqu": "0", "trPrc": "0"}, {"basDt": "20250224", "idxNm": "\uc5d4\uc120\ubb3c\uc9c0\uc218", "clpr": "503.9", "vs": "1.06", "fltRt": ".21", "mkp": "505.53", "hipr": "507.8", "lopr": "503.53", "trqu": "0", "trPrc": "0"}, {"basDt": "20250224", "idxNm": "\uc720\ub85c\uc120\ubb3c \ub808\ubc84\ub9ac\uc9c0\uc9c0\uc218", "clpr": "733.77", "vs": "-5.48", "fltRt": "-.74", "mkp": "739.08", "hipr": "739.08", "lopr": "733.77", "trqu": "0", "trPrc": "0"}, {"basDt": "20250224", "idxNm": "\uc720\ub85c\uc120\ubb3c \uc778\ubc84\uc2a4-2X\uc9c0\uc218", "clpr": "607.68", "vs": "4.33", "fltRt": ".72", "mkp": "603.35", "hipr": "607.68", "lopr": "603.35", "trqu": "0", "trPrc": "0"}, {"basDt": "20250224", "idxNm": "\uc720\ub85c\uc120\ubb3c \uc778\ubc84\uc2a4-3X\uc9c0\uc218", "clpr": "464.71", "vs": "4.95", "fltRt": "1.08", "mkp": "459.76", "hipr": "464.71", "lopr": "459.76", "trqu": "0", "trPrc": "0"}, {"basDt": "20250224", "idxNm": "\uc720\ub85c\uc120\ubb3c \uc778\ubc84\uc2a4\uc9c0\uc218", "clpr": "886.37", "vs": "3.37", "fltRt": ".38", "mkp": "883.2", "hipr": "886.37", "lopr": "883.2", "trqu": "0", "trPrc": "0"}, {"basDt": "20250224", "idxNm": "\uc720\ub85c\uc120\ubb3c\uc9c0\uc218", "clpr": "893.54", "vs": "-3.22", "fltRt": "-.36", "mkp": "896.76", "hipr": "896.76", "lopr": "893.54", "trqu": "0", "trPrc": "0"}, {"basDt": "20250224", "idxNm": "\uc8fc\uc2dd\uace8\ub4dc\uc9c0\uc218", "clpr": "6078.18", "vs": "-20.13", "fltRt": "-.33", "mkp": "6069.17", "hipr": "6078.18", "lopr": "6056.78", "trqu": "0", "trPrc": "0"}, {"basDt": "20250224", "idxNm": "\uc8fc\uc2dd\uad6d\ucc44\ud63c\ud569(\uc8fc\uc2dd\ud615)\uc9c0\uc218", "clpr": "1643.68", "vs": "-6.46", "fltRt": "-.39", "mkp": "1640.15", "hipr": "1643.68", "lopr": "1635.67", "trqu": "0", "trPrc": "0"}, {"basDt": "20250224", "idxNm": "\uc8fc\uc2dd\uad6d\ucc44\ud63c\ud569(\ucc44\uad8c\ud615)\uc9c0\uc218", "clpr": "1642.01", "vs": "-2.43", "fltRt": "-.15", "mkp": "1640.27", "hipr": "1642.13", "lopr": "1638.73", "trqu": "0", "trPrc": "0"}, {"basDt": "20250224", "idxNm": "\uc8fc\uc2dd\ubbf8\uad6d\ucc44DAE\uc9c0\uc218", "clpr": "4867.05", "vs": "-8.38", "fltRt": "-.17", "mkp": "4858.12", "hipr": "4867.05", "lopr": "4845.84", "trqu": "0", "trPrc": "0"}, {"basDt": "20250224", "idxNm": "\ucf54\ub9ac\uc544 \ubc38\ub958\uc5c5 TR \uc9c0\uc218", "clpr": "1048.9", "vs": "-6.3", "fltRt": "-.6", "mkp": "1046.47", "hipr": "1048.9", "lopr": "1040.92", "trqu": "0", "trPrc": "0"}, {"basDt": "20250224", "idxNm": "\ucf54\uc2a4\ub2e5 150 TR", "clpr": "1412.47", "vs": "2.15", "fltRt": ".15", "mkp": "1393.51", "hipr": "1413.39", "lopr": "1391.64", "trqu": "0", "trPrc": "0"}, {"basDt": "20250224", "idxNm": "\ucf54\uc2a4\ub2e5 150 \ub3d9\uc77c\uac00\uc911\uc9c0\uc218", "clpr": "1052.97", "vs": "-4.58", "fltRt": "-.43", "mkp": "1044.09", "hipr": "1052.97", "lopr": "1040.02", "trqu": "69175498", "trPrc": "2661851877735"}, {"basDt": "20250224", "idxNm": "\ucf54\uc2a4\ub2e5 150 \ub808\ubc84\ub9ac\uc9c00.5\uc9c0\uc218", "clpr": "1451.76", "vs": "1.28", "fltRt": ".09", "mkp": "1442.01", "hipr": "1452.23", "lopr": "1441.05", "trqu": "0", "trPrc": "0"}, {"basDt": "20250224", "idxNm": "\ucf54\uc2a4\ub2e5 150 \ub808\ubc84\ub9ac\uc9c0\uc9c0\uc218", "clpr": "664.3", "vs": "1.86", "fltRt": ".28", "mkp": "646.49", "hipr": "665.17", "lopr": "644.73", "trqu": "0", "trPrc": "0"}, {"basDt": "20250224", "idxNm": "\ucf54\uc2a4\ub2e5 150 \ubbf8\uad6d\ub2ec\ub7ec \ud604\uc120\ubb3c\ud63c\ud569\uc9c0\uc218", "clpr": "1818.51", "vs": "-6.64", "fltRt": "-.36", "mkp": "1807.26", "hipr": "1820.42", "lopr": "1796.77", "trqu": "0", "trPrc": "0"}, {"basDt": "20250224", "idxNm": "\ucf54\uc2a4\ub2e5 150 \uc120\ubb3c TWAP 0.5X \uc9c0\uc218", "clpr": "1780.19", "vs": "-.42", "fltRt": "-.02", "mkp": "1768.77", "hipr": "1782.89", "lopr": "1767.29", "trqu": "0", "trPrc": "0"}, {"basDt": "20250224", "idxNm": "\ucf54\uc2a4\ub2e5 150 \uc120\ubb3c TWAP \ub808\ubc84\ub9ac\uc9c0\uc9c0\uc218", "clpr": "1172.78", "vs": "-1.93", "fltRt": "-.16", "mkp": "1142.63", "hipr": "1179.9", "lopr": "1138.72", "trqu": "0", "trPrc": "0"}, {"basDt": "20250224", "idxNm": "\ucf54\uc2a4\ub2e5 150 \uc120\ubb3c TWAP \uc6d4\uac04 \ub808\ubc84\ub9ac\uc9c0 \uc9c0\uc218", "clpr": "1297.22", "vs": "-2.06", "fltRt": "-.16", "mkp": "1265.15", "hipr": "1304.79", "lopr": "1260.98", "trqu": "0", "trPrc": "0"}, {"basDt": "20250224", "idxNm": "\ucf54\uc2a4\ub2e5 150 \uc120\ubb3c TWAP \uc6d4\uac04 \uc778\ubc84\uc2a4 -2X \uc9c0\uc218", "clpr": "835.47", "vs": "1.87", "fltRt": ".22", "mkp": "859.69", "hipr": "862.84", "lopr": "829.75", "trqu": "0", "trPrc": "0"}, {"basDt": "20250224", "idxNm": "\ucf54\uc2a4\ub2e5 150 \uc120\ubb3c TWAP \uc778\ubc84\uc2a4-2X\uc9c0\uc218", "clpr": "589.1", "vs": "1.17", "fltRt": ".2", "mkp": "604.18", "hipr": "606.14", "lopr": "585.53", "trqu": "0", "trPrc": "0"}, {"basDt": "20250224", "idxNm": "\ucf54\uc2a4\ub2e5 150 \uc120\ubb3c TWAP \uc778\ubc84\uc2a4\uc9c0\uc218", "clpr": "1202.95", "vs": "1.34", "fltRt": ".11", "mkp": "1218.36", "hipr": "1220.37", "lopr": "1199.3", "trqu": "0", "trPrc": "0"}, {"basDt": "20250224", "idxNm": "\ucf54\uc2a4\ub2e5 150 \uc120\ubb3c \ub808\ubc84\ub9ac\uc9c0 1.5X \uc9c0\uc218", "clpr": "1660.46", "vs": "-1.96", "fltRt": "-.12", "mkp": "1628.48", "hipr": "1668.03", "lopr": "1624.31", "trqu": "0", "trPrc": "0"}, {"basDt": "20250224", "idxNm": "\ucf54\uc2a4\ub2e5 150 \uc120\ubb3c \ub808\ubc84\ub9ac\uc9c0\uc9c0\uc218", "clpr": "1264.37", "vs": "-2.09", "fltRt": "-.17", "mkp": "1231.88", "hipr": "1272.06", "lopr": "1227.65", "trqu": "0", "trPrc": "0"}, {"basDt": "20250224", "idxNm": "\ucf54\uc2a4\ub2e5 150 \uc120\ubb3c \uc778\ubc84\uc2a4-2X\uc9c0\uc218", "clpr": "52.73", "vs": ".1", "fltRt": ".19", "mkp": "54.08", "hipr": "54.26", "lopr": "52.42", "trqu": "0", "trPrc": "0"}, {"basDt": "20250224", "idxNm": "\ucf54\uc2a4\ub2e5 150 \uc120\ubb3c \uc778\ubc84\uc2a4-3X\uc9c0\uc218", "clpr": "3.42", "vs": ".01", "fltRt": ".29", "mkp": "3.55", "hipr": "3.57", "lopr": "3.39", "trqu": "0", "trPrc": "0"}, {"basDt": "20250224", "idxNm": "\ucf54\uc2a4\ub2e5 150 \uc120\ubb3c \uc778\ubc84\uc2a4\uc9c0\uc218", "clpr": "373.61", "vs": ".42", "fltRt": ".11", "mkp": "378.39", "hipr": "379.02", "lopr": "372.47", "trqu": "0", "trPrc": "0"}, {"basDt": "20250224", "idxNm": "\ucf54\uc2a4\ub2e5 150 \uc120\ubb3c\uc9c0\uc218", "clpr": "1537.67", "vs": "-1.4", "fltRt": "-.09", "mkp": "1517.93", "hipr": "1542.34", "lopr": "1515.36", "trqu": "0", "trPrc": "0"}, {"basDt": "20250224", "idxNm": "\ucf54\uc2a4\ub2e5 150 \uc120\ubb3c\uc9c0\uc218 TWAP\ud615", "clpr": "1539.6", "vs": "-1.4", "fltRt": "-.09", "mkp": "1519.83", "hipr": "1544.27", "lopr": "1517.26", "trqu": "0", "trPrc": "0"}, {"basDt": "20250224", "idxNm": "\ucf54\uc2a4\ub2e5 TR", "clpr": "849.6", "vs": "-1.45", "fltRt": "-.17", "mkp": "842.58", "hipr": "849.8", "lopr": "839.88", "trqu": "0", "trPrc": "0"}, {"basDt": "20250224", "idxNm": "\ucf54\uc2a4\ub2e5150 \ub871 100% \ucf54\uc2a4\ud53c200 \uc20f 100% \uc120\ubb3c\uc9c0\uc218", "clpr": "1206.33", "vs": "10.71", "fltRt": ".9", "mkp": "1192.64", "hipr": "1208.16", "lopr": "1189.51", "trqu": "0", "trPrc": "0"}, {"basDt": "20250224", "idxNm": "\ucf54\uc2a4\ub2e5150 \ub871 100% \ucf54\uc2a4\ud53c200 \uc20f 50% \uc120\ubb3c\uc9c0\uc218", "clpr": "1532.97", "vs": "6.3", "fltRt": ".41", "mkp": "1514.72", "hipr": "1536.39", "lopr": "1511.16", "trqu": "0", "trPrc": "0"}, {"basDt": "20250224", "idxNm": "\ucf54\uc2a4\ud53c 100 \ub3d9\uc77c\uac00\uc911\uc9c0\uc218", "clpr": "2120.45", "vs": "-2.61", "fltRt": "-.12", "mkp": "2112.03", "hipr": "2122.44", "lopr": "2105.48", "trqu": "159023321", "trPrc": "7540986763257"}, {"basDt": "20250224", "idxNm": "\ucf54\uc2a4\ud53c 200 DAE \uc9c0\uc218", "clpr": "1462.58", "vs": "-3.76", "fltRt": "-.26", "mkp": "1459.75", "hipr": "1462.87", "lopr": "1456.35", "trqu": "0", "trPrc": "0"}, {"basDt": "20250224", "idxNm": "\ucf54\uc2a4\ud53c 200 NTR", "clpr": "433.24", "vs": "-2.5", "fltRt": "-.57", "mkp": "432.1", "hipr": "433.24", "lopr": "430.16", "trqu": "0", "trPrc": "0"}, {"basDt": "20250224", "idxNm": "\ucf54\uc2a4\ud53c 200 NTR USD", "clpr": "338.82", "vs": "-.33", "fltRt": "-.1", "mkp": "0", "hipr": "0", "lopr": "0", "trqu": "0", "trPrc": null}, {"basDt": "20250224", "idxNm": "\ucf54\uc2a4\ud53c 200 NTR \uc6d4\uac04 \ub808\ubc84\ub9ac\uc9c0 \uc9c0\uc218", "clpr": "1720.51", "vs": "-19.77", "fltRt": "-1.14", "mkp": "1711.68", "hipr": "1720.51", "lopr": "1696.64", "trqu": "0", "trPrc": "0"}, {"basDt": "20250224", "idxNm": "\ucf54\uc2a4\ud53c 200 TOP 10 \ub808\ubc84\ub9ac\uc9c0", "clpr": "934.23", "vs": "-5.36", "fltRt": "-.57", "mkp": "922.3", "hipr": "934.23", "lopr": "919.95", "trqu": "0", "trPrc": "0"}, {"basDt": "20250224", "idxNm": "\ucf54\uc2a4\ud53c 200 TR", "clpr": "450.92", "vs": "-2.6", "fltRt": "-.57", "mkp": "449.73", "hipr": "450.92", "lopr": "447.71", "trqu": "0", "trPrc": "0"}, {"basDt": "20250224", "idxNm": "\ucf54\uc2a4\ud53c 200 TR USD", "clpr": "357.97", "vs": "-.35", "fltRt": "-.1", "mkp": "0", "hipr": "0", "lopr": "0", "trqu": "0", "trPrc": null}, {"basDt": "20250224", "idxNm": "\ucf54\uc2a4\ud53c 200 \uac00\uce58\uc800\ubcc0\ub3d9\uc131", "clpr": "5549.99", "vs": "-14.45", "fltRt": "-.26", "mkp": "5535.99", "hipr": "5554.03", "lopr": "5519.39", "trqu": "170577205", "trPrc": "6978636091212"}, {"basDt": "20250224", "idxNm": "\ucf54\uc2a4\ud53c 200 \uac74\uc124 TR", "clpr": "358.91", "vs": "-2.07", "fltRt": "-.57", "mkp": "358.13", "hipr": "360.37", "lopr": "354.57", "trqu": "0", "trPrc": "0"}, {"basDt": "20250224", "idxNm": "\ucf54\uc2a4\ud53c 200 \uac74\uc124 \ub808\ubc84\ub9ac\uc9c0\uc9c0\uc218", "clpr": "156.6", "vs": "-1.85", "fltRt": "-1.17", "mkp": "155.91", "hipr": "157.88", "lopr": "152.78", "trqu": "0", "trPrc": "0"}, {"basDt": "20250224", "idxNm": "\ucf54\uc2a4\ud53c 200 \uac74\uc124 \uc120\ubb3c\ub808\ubc84\ub9ac\uc9c0 \uc9c0\uc218", "clpr": "801.24", "vs": "-33.96", "fltRt": "-4.07", "mkp": "835.34", "hipr": "835.34", "lopr": "797.93", "trqu": "0", "trPrc": "0"}, {"basDt": "20250224", "idxNm": "\ucf54\uc2a4\ud53c 200 \uac74\uc124 \uc120\ubb3c\uc778\ubc84\uc2a4 \uc9c0\uc218", "clpr": "579.83", "vs": "11.72", "fltRt": "2.06", "mkp": "568.23", "hipr": "580.95", "lopr": "568.23", "trqu": "0", "trPrc": "0"}, {"basDt": "20250224", "idxNm": "\ucf54\uc2a4\ud53c 200 \uac74\uc124 \uc120\ubb3c\uc778\ubc84\uc2a4-2X \uc9c0\uc218", "clpr": "158.93", "vs": "6.26", "fltRt": "4.1", "mkp": "152.7", "hipr": "159.54", "lopr": "152.7", "trqu": "0", "trPrc": "0"}, {"basDt": "20250224", "idxNm": "\ucf54\uc2a4\ud53c 200 \uac74\uc124 \uc120\ubb3c\uc9c0\uc218", "clpr": "1124.47", "vs": "-23.44", "fltRt": "-2.04", "mkp": "1147.91", "hipr": "1147.91", "lopr": "1122.2", "trqu": "0", "trPrc": "0"}, {"basDt": "20250224", "idxNm": "\ucf54\uc2a4\ud53c 200 \uacbd\uae30\uc18c\ube44\uc7ac TR", "clpr": "2053.22", "vs": "4.04", "fltRt": ".2", "mkp": "2038.21", "hipr": "2053.29", "lopr": "2028.73", "trqu": "0", "trPrc": "0"}, {"basDt": "20250224", "idxNm": "\ucf54\uc2a4\ud53c 200 \uacbd\uae30\uc18c\ube44\uc7ac \ub808\ubc84\ub9ac\uc9c0\uc9c0\uc218", "clpr": "769.5", "vs": "2.84", "fltRt": ".37", "mkp": "758.27", "hipr": "769.56", "lopr": "751.18", "trqu": "0", "trPrc": "0"}, {"basDt": "20250224", "idxNm": "\ucf54\uc2a4\ud53c 200 \uacbd\uae30\uc18c\ube44\uc7ac \uc120\ubb3c\ub808\ubc84\ub9ac\uc9c0 \uc9c0\uc218", "clpr": "831.3", "vs": "-5.78", "fltRt": "-.69", "mkp": "837.24", "hipr": "837.24", "lopr": "819.01", "trqu": "0", "trPrc": "0"}, {"basDt": "20250224", "idxNm": "\ucf54\uc2a4\ud53c 200 \uacbd\uae30\uc18c\ube44\uc7ac \uc120\ubb3c\uc778\ubc84\uc2a4 \uc9c0\uc218", "clpr": "765.48", "vs": "2.87", "fltRt": ".38", "mkp": "762.77", "hipr": "771.07", "lopr": "762.77", "trqu": "0", "trPrc": "0"}, {"basDt": "20250224", "idxNm": "\ucf54\uc2a4\ud53c 200 \uacbd\uae30\uc18c\ube44\uc7ac \uc120\ubb3c\uc778\ubc84\uc2a4-2X \uc9c0\uc218", "clpr": "330.14", "vs": "2.39", "fltRt": ".73", "mkp": "327.81", "hipr": "334.95", "lopr": "327.81", "trqu": "0", "trPrc": "0"}, {"basDt": "20250224", "idxNm": "\ucf54\uc2a4\ud53c 200 \uacbd\uae30\uc18c\ube44\uc7ac \uc120\ubb3c\uc9c0\uc218", "clpr": "1031.37", "vs": "-3.67", "fltRt": "-.35", "mkp": "1035.04", "hipr": "1035.04", "lopr": "1023.77", "trqu": "0", "trPrc": "0"}, {"basDt": "20250224", "idxNm": "\ucf54\uc2a4\ud53c 200 \uace0\ubc30\ub2f9 \ucee4\ubc84\ub4dc\ucf5c ATM", "clpr": "1338.44", "vs": "9.46", "fltRt": ".71", "mkp": "1333.27", "hipr": "1338.53", "lopr": "1328.82", "trqu": "0", "trPrc": "0"}, {"basDt": "20250224", "idxNm": "\ucf54\uc2a4\ud53c 200 \uace0\ubc30\ub2f9\uc9c0\uc218", "clpr": "3468.52", "vs": "2.96", "fltRt": ".09", "mkp": "3447.93", "hipr": "3468.67", "lopr": "3444.23", "trqu": "31743455", "trPrc": "1529222453931"}, {"basDt": "20250224", "idxNm": "\ucf54\uc2a4\ud53c 200 \uae08\uc735 TR", "clpr": "1422.8", "vs": "-1.56", "fltRt": "-.11", "mkp": "1421.26", "hipr": "1427.01", "lopr": "1414.12", "trqu": "0", "trPrc": "0"}, {"basDt": "20250224", "idxNm": "\ucf54\uc2a4\ud53c 200 \uae08\uc735 \uace0\ubc30\ub2f9 TOP 10 TR \uc9c0\uc218", "clpr": "1998.05", "vs": "-2.96", "fltRt": "-.15", "mkp": "1996.45", "hipr": "2004.17", "lopr": "1984.1", "trqu": "0", "trPrc": "0"}, {"basDt": "20250224", "idxNm": "\ucf54\uc2a4\ud53c 200 \uae08\uc735 \uace0\ubc30\ub2f9 TOP 10 \ud0c0\uac9f \uc704\ud074\ub9ac \ucee4\ubc84\ub4dc\ucf5c \uc9c0\uc218", "clpr": "871.12", "vs": "-.59", "fltRt": "-.07", "mkp": "872.38", "hipr": "873.75", "lopr": "865", "trqu": "0", "trPrc": "0"}, {"basDt": "20250224", "idxNm": "\ucf54\uc2a4\ud53c 200 \uae08\uc735 \uace0\ubc30\ub2f9 TOP 10 \ud0c0\uac9f \ucee4\ubc84\ub9ac\uc9c0 \uc704\ud074\ub9ac \ucee4\ubc84\ub4dc\ucf5c \uc9c0\uc218", "clpr": "1942.64", "vs": "-1.32", "fltRt": "-.07", "mkp": "1945.46", "hipr": "1948.5", "lopr": "1928.99", "trqu": "0", "trPrc": "0"}, {"basDt": "20250224", "idxNm": "\ucf54\uc2a4\ud53c 200 \uae08\uc735 \ub808\ubc84\ub9ac\uc9c0\uc9c0\uc218", "clpr": "594.46", "vs": "-1.44", "fltRt": "-.24", "mkp": "593.17", "hipr": "597.98", "lopr": "587.19", "trqu": "0", "trPrc": "0"}, {"basDt": "20250224", "idxNm": "\ucf54\uc2a4\ud53c 200 \uae08\uc735 \uc120\ubb3c\ub808\ubc84\ub9ac\uc9c0 \uc9c0\uc218", "clpr": "1627.71", "vs": "-41.37", "fltRt": "-2.48", "mkp": "1669.37", "hipr": "1669.37", "lopr": "1608.04", "trqu": "0", "trPrc": "0"}, {"basDt": "20250224", "idxNm": "\ucf54\uc2a4\ud53c 200 \uae08\uc735 \uc120\ubb3c\uc778\ubc84\uc2a4 \uc9c0\uc218", "clpr": "517.17", "vs": "6.48", "fltRt": "1.27", "mkp": "510.79", "hipr": "520.18", "lopr": "510.79", "trqu": "0", "trPrc": "0"}, {"basDt": "20250224", "idxNm": "\ucf54\uc2a4\ud53c 200 \uae08\uc735 \uc120\ubb3c\uc778\ubc84\uc2a4-2X \uc9c0\uc218", "clpr": "146.97", "vs": "3.6", "fltRt": "2.51", "mkp": "143.39", "hipr": "148.66", "lopr": "143.39", "trqu": "0", "trPrc": "0"}, {"basDt": "20250224", "idxNm": "\ucf54\uc2a4\ud53c 200 \uae08\uc735 \uc120\ubb3c\uc9c0\uc218", "clpr": "1474.25", "vs": "-18.63", "fltRt": "-1.25", "mkp": "1492.88", "hipr": "1492.88", "lopr": "1465.45", "trqu": "0", "trPrc": "0"}, {"basDt": "20250224", "idxNm": "\ucf54\uc2a4\ud53c 200 \ub3d9\uc77c\uac00\uc911\uc9c0\uc218", "clpr": "2323.76", "vs": "-4.51", "fltRt": "-.19", "mkp": "2315.21", "hipr": "2326.49", "lopr": "2306.27", "trqu": "197135572", "trPrc": "8664869396852"}, {"basDt": "20250224", "idxNm": "\ucf54\uc2a4\ud53c 200 \ub808\ubc84\ub9ac\uc9c0\uc9c0\uc218", "clpr": "263.68", "vs": "-3.13", "fltRt": "-1.17", "mkp": "262.29", "hipr": "263.68", "lopr": "259.91", "trqu": "0", "trPrc": "0"}, {"basDt": "20250224", "idxNm": "\ucf54\uc2a4\ud53c 200 \ub9ac\uc2a4\ud06c\ucee8\ud2b8\ub864 10% \uc9c0\uc218", "clpr": "1537.37", "vs": "-3.78", "fltRt": "-.25", "mkp": "1535.32", "hipr": "1537.37", "lopr": "1532.5", "trqu": "0", "trPrc": "0"}, {"basDt": "20250224", "idxNm": "\ucf54\uc2a4\ud53c 200 \ub9ac\uc2a4\ud06c\ucee8\ud2b8\ub864 12% \uc9c0\uc218", "clpr": "1483.49", "vs": "-4.45", "fltRt": "-.3", "mkp": "1481.12", "hipr": "1483.49", "lopr": "1477.85", "trqu": "0", "trPrc": "0"}, {"basDt": "20250224", "idxNm": "\ucf54\uc2a4\ud53c 200 \ub9ac\uc2a4\ud06c\ucee8\ud2b8\ub864 6% \uc9c0\uc218", "clpr": "1625.29", "vs": "-2.24", "fltRt": "-.14", "mkp": "1623.99", "hipr": "1625.29", "lopr": "1622.2", "trqu": "0", "trPrc": "0"}, {"basDt": "20250224", "idxNm": "\ucf54\uc2a4\ud53c 200 \ub9ac\uc2a4\ud06c\ucee8\ud2b8\ub864 8% \uc9c0\uc218", "clpr": "1588.34", "vs": "-3.05", "fltRt": "-.19", "mkp": "1586.65", "hipr": "1588.34", "lopr": "1584.32", "trqu": "0", "trPrc": "0"}, {"basDt": "20250224", "idxNm": "\ucf54\uc2a4\ud53c 200 \ubbf8\uad6d\ucc44 \ud63c\ud569\uc9c0\uc218", "clpr": "3052.66", "vs": "-6.85", "fltRt": "-.22", "mkp": "3057.54", "hipr": "3064.1", "lopr": "3045.26", "trqu": "0", "trPrc": "0"}, {"basDt": "20250224", "idxNm": "\ucf54\uc2a4\ud53c 200 \ubcc0\ub3d9\uc131\uc9c0\uc218", "clpr": "19.48", "vs": ".84", "fltRt": "4.51", "mkp": "19.98", "hipr": "20.04", "lopr": "19.38", "trqu": "0", "trPrc": "0"}, {"basDt": "20250224", "idxNm": "\ucf54\uc2a4\ud53c 200 \ube44\uc911\uc0c1\ud55c 20% NTR", "clpr": "426.39", "vs": "-2.2", "fltRt": "-.51", "mkp": "425.06", "hipr": "426.39", "lopr": "423.21", "trqu": "0", "trPrc": "0"}, {"basDt": "20250224", "idxNm": "\ucf54\uc2a4\ud53c 200 \ube44\uc911\uc0c1\ud55c 20% NTR USD", "clpr": "333.96", "vs": "-.12", "fltRt": "-.04", "mkp": "0", "hipr": "0", "lopr": "0", "trqu": "0", "trPrc": null}, {"basDt": "20250224", "idxNm": "\ucf54\uc2a4\ud53c 200 \ube44\uc911\uc0c1\ud55c 20% TR", "clpr": "442.92", "vs": "-2.29", "fltRt": "-.51", "mkp": "441.55", "hipr": "442.92", "lopr": "439.62", "trqu": "0", "trPrc": "0"}, {"basDt": "20250224", "idxNm": "\ucf54\uc2a4\ud53c 200 \ube44\uc911\uc0c1\ud55c 20% TR USD", "clpr": "353.28", "vs": "-.12", "fltRt": "-.03", "mkp": "0", "hipr": "0", "lopr": "0", "trqu": "0", "trPrc": null}, {"basDt": "20250224", "idxNm": "\ucf54\uc2a4\ud53c 200 \ube44\uc911\uc0c1\ud55c 25% NTR", "clpr": "433.7", "vs": "-2.5", "fltRt": "-.57", "mkp": "432.56", "hipr": "433.7", "lopr": "430.61", "trqu": "0", "trPrc": "0"}, {"basDt": "20250224", "idxNm": "\ucf54\uc2a4\ud53c 200 \ube44\uc911\uc0c1\ud55c 25% NTR USD", "clpr": "337.73", "vs": "-.33", "fltRt": "-.1", "mkp": "0", "hipr": "0", "lopr": "0", "trqu": "0", "trPrc": null}, {"basDt": "20250224", "idxNm": "\ucf54\uc2a4\ud53c 200 \ube44\uc911\uc0c1\ud55c 25% TR", "clpr": "451.13", "vs": "-2.6", "fltRt": "-.57", "mkp": "449.94", "hipr": "451.13", "lopr": "447.92", "trqu": "0", "trPrc": "0"}, {"basDt": "20250224", "idxNm": "\ucf54\uc2a4\ud53c 200 \ube44\uc911\uc0c1\ud55c 25% TR USD", "clpr": "357.41", "vs": "-.34", "fltRt": "-.1", "mkp": "0", "hipr": "0", "lopr": "0", "trqu": "0", "trPrc": null}, {"basDt": "20250224", "idxNm": "\ucf54\uc2a4\ud53c 200 \ube44\uc911\uc0c1\ud55c 30% NTR", "clpr": "433.22", "vs": "-2.5", "fltRt": "-.57", "mkp": "432.08", "hipr": "433.22", "lopr": "430.15", "trqu": "0", "trPrc": "0"}, {"basDt": "20250224", "idxNm": "\ucf54\uc2a4\ud53c 200 \ube44\uc911\uc0c1\ud55c 30% NTR USD", "clpr": "338.55", "vs": "-.33", "fltRt": "-.1", "mkp": "0", "hipr": "0", "lopr": "0", "trqu": "0", "trPrc": null}, {"basDt": "20250224", "idxNm": "\ucf54\uc2a4\ud53c 200 \ube44\uc911\uc0c1\ud55c 30% TR", "clpr": "450.61", "vs": "-2.6", "fltRt": "-.57", "mkp": "449.42", "hipr": "450.61", "lopr": "447.41", "trqu": "0", "trPrc": "0"}, {"basDt": "20250224", "idxNm": "\ucf54\uc2a4\ud53c 200 \ube44\uc911\uc0c1\ud55c 30% TR USD", "clpr": "357.8", "vs": "-.35", "fltRt": "-.1", "mkp": "0", "hipr": "0", "lopr": "0", "trqu": "0", "trPrc": null}, {"basDt": "20250224", "idxNm": "\ucf54\uc2a4\ud53c 200 \uc0b0\uc5c5\uc7ac TR", "clpr": "953.04", "vs": "11.06", "fltRt": "1.17", "mkp": "942.86", "hipr": "956.56", "lopr": "940.8", "trqu": "0", "trPrc": "0"}, {"basDt": "20250224", "idxNm": "\ucf54\uc2a4\ud53c 200 \uc0b0\uc5c5\uc7ac \uc120\ubb3c\ub808\ubc84\ub9ac\uc9c0 \uc9c0\uc218", "clpr": "1189.83", "vs": "25.87", "fltRt": "2.22", "mkp": "1164.16", "hipr": "1196.98", "lopr": "1164.16", "trqu": "0", "trPrc": "0"}, {"basDt": "20250224", "idxNm": "\ucf54\uc2a4\ud53c 200 \uc0b0\uc5c5\uc7ac \uc120\ubb3c\uc778\ubc84\uc2a4 \uc9c0\uc218", "clpr": "653.12", "vs": "-7.14", "fltRt": "-1.08", "mkp": "660.4", "hipr": "660.4", "lopr": "651.09", "trqu": "0", "trPrc": "0"}, {"basDt": "20250224", "idxNm": "\ucf54\uc2a4\ud53c 200 \uc0b0\uc5c5\uc7ac \uc120\ubb3c\uc778\ubc84\uc2a4-2X \uc9c0\uc218", "clpr": "246.43", "vs": "-5.51", "fltRt": "-2.19", "mkp": "251.98", "hipr": "251.98", "lopr": "244.88", "trqu": "0", "trPrc": "0"}, {"basDt": "20250224", "idxNm": "\ucf54\uc2a4\ud53c 200 \uc0b0\uc5c5\uc7ac \uc120\ubb3c\uc9c0\uc218", "clpr": "1227.76", "vs": "13.39", "fltRt": "1.1", "mkp": "1214.37", "hipr": "1231.49", "lopr": "1214.37", "trqu": "0", "trPrc": "0"}, {"basDt": "20250224", "idxNm": "\ucf54\uc2a4\ud53c 200 \uc0dd\ud65c\uc18c\ube44\uc7ac TR", "clpr": "1149.23", "vs": "-3.43", "fltRt": "-.3", "mkp": "1144.57", "hipr": "1153.56", "lopr": "1142.88", "trqu": "0", "trPrc": "0"}, {"basDt": "20250224", "idxNm": "\ucf54\uc2a4\ud53c 200 \uc0dd\ud65c\uc18c\ube44\uc7ac \uc120\ubb3c\ub808\ubc84\ub9ac\uc9c0 \uc9c0\uc218", "clpr": "412.77", "vs": "-4.33", "fltRt": "-1.04", "mkp": "417.18", "hipr": "417.18", "lopr": "409.72", "trqu": "0", "trPrc": "0"}, {"basDt": "20250224", "idxNm": "\ucf54\uc2a4\ud53c 200 \uc0dd\ud65c\uc18c\ube44\uc7ac \uc120\ubb3c\uc778\ubc84\uc2a4 \uc9c0\uc218", "clpr": "1403.35", "vs": "7.67", "fltRt": ".55", "mkp": "1395.98", "hipr": "1408.46", "lopr": "1395.98", "trqu": "0", "trPrc": "0"}, {"basDt": "20250224", "idxNm": "\ucf54\uc2a4\ud53c 200 \uc0dd\ud65c\uc18c\ube44\uc7ac \uc120\ubb3c\uc778\ubc84\uc2a4-2X \uc9c0\uc218", "clpr": "1334.57", "vs": "14.21", "fltRt": "1.08", "mkp": "1320.62", "hipr": "1344.23", "lopr": "1320.62", "trqu": "0", "trPrc": "0"}, {"basDt": "20250224", "idxNm": "\ucf54\uc2a4\ud53c 200 \uc0dd\ud65c\uc18c\ube44\uc7ac \uc120\ubb3c\uc9c0\uc218", "clpr": "668.5", "vs": "-3.55", "fltRt": "-.53", "mkp": "672.05", "hipr": "672.05", "lopr": "666.04", "trqu": "0", "trPrc": "0"}, {"basDt": "20250224", "idxNm": "\ucf54\uc2a4\ud53c 200 \uc120\ubb3c TWAP 0.5X \uc9c0\uc218", "clpr": "2166.64", "vs": "-10.06", "fltRt": "-.46", "mkp": "2165.56", "hipr": "2169.28", "lopr": "2162.15", "trqu": "0", "trPrc": "0"}, {"basDt": "20250224", "idxNm": "\ucf54\uc2a4\ud53c 200 \uc120\ubb3c TWAP \ub808\ubc84\ub9ac\uc9c0\uc9c0\uc218", "clpr": "1319.37", "vs": "-25.82", "fltRt": "-1.92", "mkp": "1316.69", "hipr": "1325.89", "lopr": "1308.26", "trqu": "0", "trPrc": "0"}, {"basDt": "20250224", "idxNm": "\ucf54\uc2a4\ud53c 200 \uc120\ubb3c TWAP \uc6d4\uac04 \ub808\ubc84\ub9ac\uc9c0 \uc9c0\uc218", "clpr": "1342.02", "vs": "-25.41", "fltRt": "-1.86", "mkp": "1339.39", "hipr": "1348.44", "lopr": "1331.09", "trqu": "0", "trPrc": "0"}, {"basDt": "20250224", "idxNm": "\ucf54\uc2a4\ud53c 200 \uc120\ubb3c TWAP \uc6d4\uac04 \uc778\ubc84\uc2a4 -2X \uc9c0\uc218", "clpr": "2735", "vs": "58.09", "fltRt": "2.17", "mkp": "2740.91", "hipr": "2759.51", "lopr": "2720.6", "trqu": "0", "trPrc": "0"}, {"basDt": "20250224", "idxNm": "\ucf54\uc2a4\ud53c 200 \uc120\ubb3c TWAP \uc778\ubc84\uc2a4-2X\uc9c0\uc218", "clpr": "2535.98", "vs": "48.69", "fltRt": "1.96", "mkp": "2540.93", "hipr": "2556.52", "lopr": "2523.92", "trqu": "0", "trPrc": "0"}, {"basDt": "20250224", "idxNm": "\ucf54\uc2a4\ud53c 200 \uc120\ubb3c TWAP \uc778\ubc84\uc2a4\uc9c0\uc218", "clpr": "2623.92", "vs": "25.74", "fltRt": ".99", "mkp": "2626.5", "hipr": "2634.64", "lopr": "2617.62", "trqu": "0", "trPrc": "0"}, {"basDt": "20250224", "idxNm": "\ucf54\uc2a4\ud53c 200 \uc120\ubb3c \ub808\ubc84\ub9ac\uc9c0 1.5X \uc9c0\uc218", "clpr": "2208.36", "vs": "-32.09", "fltRt": "-1.43", "mkp": "2205", "hipr": "2216.5", "lopr": "2194.46", "trqu": "0", "trPrc": "0"}, {"basDt": "20250224", "idxNm": "\ucf54\uc2a4\ud53c 200 \uc120\ubb3c \ub808\ubc84\ub9ac\uc9c0\uc9c0\uc218", "clpr": "2191.66", "vs": "-42.86", "fltRt": "-1.92", "mkp": "2187.21", "hipr": "2202.49", "lopr": "2173.18", "trqu": "0", "trPrc": "0"}, {"basDt": "20250224", "idxNm": "\ucf54\uc2a4\ud53c 200 \uc120\ubb3c \uc778\ubc84\uc2a4-2X\uc9c0\uc218", "clpr": "257.67", "vs": "4.94", "fltRt": "1.95", "mkp": "258.18", "hipr": "259.76", "lopr": "256.45", "trqu": "0", "trPrc": "0"}, {"basDt": "20250224", "idxNm": "\ucf54\uc2a4\ud53c 200 \uc120\ubb3c \uc778\ubc84\uc2a4-3X\uc9c0\uc218", "clpr": "66.78", "vs": "1.9", "fltRt": "2.93", "mkp": "66.97", "hipr": "67.58", "lopr": "66.3", "trqu": "0", "trPrc": "0"}, {"basDt": "20250224", "idxNm": "\ucf54\uc2a4\ud53c 200 \uc120\ubb3c \uc778\ubc84\uc2a4\uc9c0\uc218", "clpr": "568.05", "vs": "5.57", "fltRt": ".99", "mkp": "568.61", "hipr": "570.37", "lopr": "566.69", "trqu": "0", "trPrc": "0"}, {"basDt": "20250224", "idxNm": "\ucf54\uc2a4\ud53c 200 \uc120\ubb3c\uc9c0\uc218", "clpr": "1716.88", "vs": "-16.79", "fltRt": "-.97", "mkp": "1715.15", "hipr": "1721.08", "lopr": "1709.71", "trqu": "0", "trPrc": "0"}, {"basDt": "20250224", "idxNm": "\ucf54\uc2a4\ud53c 200 \uc120\ubb3c\uc9c0\uc218 TWAP\ud615", "clpr": "1719.66", "vs": "-16.83", "fltRt": "-.97", "mkp": "1717.93", "hipr": "1723.87", "lopr": "1712.49", "trqu": "0", "trPrc": "0"}, {"basDt": "20250224", "idxNm": "\ucf54\uc2a4\ud53c 200 \uc5d0\ub108\uc9c0/\ud654\ud559 \ub808\ubc84\ub9ac\uc9c0\uc9c0\uc218", "clpr": "416.26", "vs": "-.89", "fltRt": "-.21", "mkp": "411.48", "hipr": "420.6", "lopr": "409.03", "trqu": "0", "trPrc": "0"}, {"basDt": "20250224", "idxNm": "\ucf54\uc2a4\ud53c 200 \uc5d0\ub108\uc9c0/\ud654\ud559 \uc120\ubb3c\ub808\ubc84\ub9ac\uc9c0 \uc9c0\uc218", "clpr": "533.98", "vs": "-.74", "fltRt": "-.14", "mkp": "534.81", "hipr": "540.87", "lopr": "528.96", "trqu": "0", "trPrc": "0"}, {"basDt": "20250224", "idxNm": "\ucf54\uc2a4\ud53c 200 \uc5d0\ub108\uc9c0/\ud654\ud559 \uc120\ubb3c\uc778\ubc84\uc2a4 \uc9c0\uc218", "clpr": "810.59", "vs": ".79", "fltRt": ".1", "mkp": "809.96", "hipr": "814.39", "lopr": "805.38", "trqu": "0", "trPrc": "0"}, {"basDt": "20250224", "idxNm": "\ucf54\uc2a4\ud53c 200 \uc5d0\ub108\uc9c0/\ud654\ud559 \uc120\ubb3c\uc778\ubc84\uc2a4-2X \uc9c0\uc218", "clpr": "335.51", "vs": ".58", "fltRt": ".17", "mkp": "334.99", "hipr": "338.65", "lopr": "331.19", "trqu": "0", "trPrc": "0"}, {"basDt": "20250224", "idxNm": "\ucf54\uc2a4\ud53c 200 \uc5d0\ub108\uc9c0/\ud654\ud559 \uc120\ubb3c\uc9c0\uc218", "clpr": "875.3", "vs": "-.68", "fltRt": "-.08", "mkp": "875.98", "hipr": "880.94", "lopr": "871.19", "trqu": "0", "trPrc": "0"}, {"basDt": "20250224", "idxNm": "\ucf54\uc2a4\ud53c 200 \uc5d0\ub108\uc9c0\ud654\ud559 TR", "clpr": "1332.67", "vs": "-1.26", "fltRt": "-.09", "mkp": "1325.03", "hipr": "1339.61", "lopr": "1321.11", "trqu": "0", "trPrc": "0"}, {"basDt": "20250224", "idxNm": "\ucf54\uc2a4\ud53c 200 \uc6d4\ubcc4 \uc591\ub9e4\ub3c4 3% OTM", "clpr": "1391.79", "vs": "5.86", "fltRt": ".42", "mkp": "1390.89", "hipr": "1392.72", "lopr": "1390.09", "trqu": "0", "trPrc": "0"}, {"basDt": "20250224", "idxNm": "\ucf54\uc2a4\ud53c 200 \uc6d4\ubcc4 \uc591\ub9e4\ub3c4 5% OTM", "clpr": "1318.5", "vs": "3.52", "fltRt": ".27", "mkp": "1317.79", "hipr": "1318.8", "lopr": "1317.38", "trqu": "0", "trPrc": "0"}, {"basDt": "20250224", "idxNm": "\ucf54\uc2a4\ud53c 200 \uc6d4\ubcc4 \uc591\ub9e4\ub3c4 ATM", "clpr": "1454.02", "vs": "6.99", "fltRt": ".48", "mkp": "1448.36", "hipr": "1455.78", "lopr": "1448.27", "trqu": "0", "trPrc": "0"}, {"basDt": "20250224", "idxNm": "\ucf54\uc2a4\ud53c 200 \uc704\ud074\ub9ac \ucee4\ubc84\ub4dc\ucf5c ATM \uc9c0\uc218", "clpr": "1150.69", "vs": "-3.83", "fltRt": "-.33", "mkp": "1157.21", "hipr": "1157.21", "lopr": "1142.52", "trqu": "0", "trPrc": "0"}, {"basDt": "20250224", "idxNm": "\ucf54\uc2a4\ud53c 200 \uc815\ubcf4\uae30\uc220 TR", "clpr": "3383.82", "vs": "-14.36", "fltRt": "-.42", "mkp": "3343.48", "hipr": "3383.82", "lopr": "3339.63", "trqu": "0", "trPrc": "0"}, {"basDt": "20250224", "idxNm": "\ucf54\uc2a4\ud53c 200 \uc815\ubcf4\uae30\uc220 \ub808\ubc84\ub9ac\uc9c0\uc9c0\uc218", "clpr": "3112.04", "vs": "-27.27", "fltRt": "-.87", "mkp": "3037.5", "hipr": "3112.04", "lopr": "3030.39", "trqu": "0", "trPrc": "0"}, {"basDt": "20250224", "idxNm": "\ucf54\uc2a4\ud53c 200 \uc815\ubcf4\uae30\uc220 \uc120\ubb3c\ub808\ubc84\ub9ac\uc9c0 \uc9c0\uc218", "clpr": "2266.97", "vs": "-32.08", "fltRt": "-1.4", "mkp": "2299.45", "hipr": "2299.45", "lopr": "2224.73", "trqu": "0", "trPrc": "0"}, {"basDt": "20250224", "idxNm": "\ucf54\uc2a4\ud53c 200 \uc815\ubcf4\uae30\uc220 \uc120\ubb3c\uc778\ubc84\uc2a4 \uc9c0\uc218", "clpr": "422.51", "vs": "3.05", "fltRt": ".73", "mkp": "419.55", "hipr": "426.36", "lopr": "419.55", "trqu": "0", "trPrc": "0"}, {"basDt": "20250224", "idxNm": "\ucf54\uc2a4\ud53c 200 \uc815\ubcf4\uae30\uc220 \uc120\ubb3c\uc778\ubc84\uc2a4-2X \uc9c0\uc218", "clpr": "96.15", "vs": "1.36", "fltRt": "1.43", "mkp": "94.81", "hipr": "97.89", "lopr": "94.81", "trqu": "0", "trPrc": "0"}, {"basDt": "20250224", "idxNm": "\ucf54\uc2a4\ud53c 200 \uc815\ubcf4\uae30\uc220 \uc120\ubb3c\uc9c0\uc218", "clpr": "1762.98", "vs": "-12.54", "fltRt": "-.71", "mkp": "1775.52", "hipr": "1775.52", "lopr": "1746.67", "trqu": "0", "trPrc": "0"}, {"basDt": "20250224", "idxNm": "\ucf54\uc2a4\ud53c 200 \uc911\uacf5\uc5c5 TR", "clpr": "712.78", "vs": "-12.65", "fltRt": "-1.74", "mkp": "723.5", "hipr": "727.8", "lopr": "698.82", "trqu": "0", "trPrc": "0"}, {"basDt": "20250224", "idxNm": "\ucf54\uc2a4\ud53c 200 \uc911\uacf5\uc5c5 \ub808\ubc84\ub9ac\uc9c0\uc9c0\uc218", "clpr": "570.08", "vs": "-20.74", "fltRt": "-3.51", "mkp": "587.53", "hipr": "594.54", "lopr": "547.34", "trqu": "0", "trPrc": "0"}, {"basDt": "20250224", "idxNm": "\ucf54\uc2a4\ud53c 200 \uc911\uacf5\uc5c5 \uc120\ubb3c\ub808\ubc84\ub9ac\uc9c0 \uc9c0\uc218", "clpr": "1745.73", "vs": "-64.64", "fltRt": "-3.57", "mkp": "1810.66", "hipr": "1810.66", "lopr": "1679.71", "trqu": "0", "trPrc": "0"}, {"basDt": "20250224", "idxNm": "\ucf54\uc2a4\ud53c 200 \uc911\uacf5\uc5c5 \uc120\ubb3c\uc778\ubc84\uc2a4 \uc9c0\uc218", "clpr": "304.14", "vs": "5.42", "fltRt": "1.81", "mkp": "298.78", "hipr": "309.58", "lopr": "298.78", "trqu": "0", "trPrc": "0"}, {"basDt": "20250224", "idxNm": "\ucf54\uc2a4\ud53c 200 \uc911\uacf5\uc5c5 \uc120\ubb3c\uc778\ubc84\uc2a4-2X \uc9c0\uc218", "clpr": "36.82", "vs": "1.28", "fltRt": "3.6", "mkp": "35.55", "hipr": "38.12", "lopr": "35.55", "trqu": "0", "trPrc": "0"}, {"basDt": "20250224", "idxNm": "\ucf54\uc2a4\ud53c 200 \uc911\uacf5\uc5c5 \uc120\ubb3c\uc9c0\uc218", "clpr": "1809.54", "vs": "-33.04", "fltRt": "-1.79", "mkp": "1842.58", "hipr": "1842.58", "lopr": "1775.94", "trqu": "0", "trPrc": "0"}, {"basDt": "20250224", "idxNm": "\ucf54\uc2a4\ud53c 200 \ucca0\uac15/\uc18c\uc7ac \uc120\ubb3c\ub808\ubc84\ub9ac\uc9c0 \uc9c0\uc218", "clpr": "680.06", "vs": "-12.64", "fltRt": "-1.82", "mkp": "692.8", "hipr": "696.57", "lopr": "679.78", "trqu": "0", "trPrc": "0"}, {"basDt": "20250224", "idxNm": "\ucf54\uc2a4\ud53c 200 \ucca0\uac15/\uc18c\uc7ac \uc120\ubb3c\uc778\ubc84\uc2a4 \uc9c0\uc218", "clpr": "601.52", "vs": "5.59", "fltRt": ".94", "mkp": "596.04", "hipr": "601.65", "lopr": "594.42", "trqu": "0", "trPrc": "0"}, {"basDt": "20250224", "idxNm": "\ucf54\uc2a4\ud53c 200 \ucca0\uac15/\uc18c\uc7ac \uc120\ubb3c\uc778\ubc84\uc2a4-2X \uc9c0\uc218", "clpr": "164.91", "vs": "3", "fltRt": "1.85", "mkp": "161.93", "hipr": "164.98", "lopr": "161.05", "trqu": "0", "trPrc": "0"}, {"basDt": "20250224", "idxNm": "\ucf54\uc2a4\ud53c 200 \ucca0\uac15/\uc18c\uc7ac \uc120\ubb3c\uc9c0\uc218", "clpr": "1049.75", "vs": "-9.74", "fltRt": "-.92", "mkp": "1059.49", "hipr": "1062.37", "lopr": "1049.53", "trqu": "0", "trPrc": "0"}, {"basDt": "20250224", "idxNm": "\ucf54\uc2a4\ud53c 200 \ucca0\uac15\uc18c\uc7ac TR", "clpr": "1291.74", "vs": "-4.66", "fltRt": "-.36", "mkp": "1291.19", "hipr": "1299.82", "lopr": "1280.15", "trqu": "0", "trPrc": "0"}, {"basDt": "20250224", "idxNm": "\ucf54\uc2a4\ud53c 200 \ucee4\ubba4\ub2c8\ucf00\uc774\uc158\uc11c\ube44\uc2a4 TR", "clpr": "2461.38", "vs": "8.49", "fltRt": ".35", "mkp": "2434.3", "hipr": "2464.04", "lopr": "2431.47", "trqu": "0", "trPrc": "0"}, {"basDt": "20250224", "idxNm": "\ucf54\uc2a4\ud53c 200 \ucee4\ubc84\ub4dc\ucf5c 5% OTM \uc9c0\uc218", "clpr": "361.43", "vs": "-1.15", "fltRt": "-.32", "mkp": "363.5", "hipr": "363.57", "lopr": "359.08", "trqu": "0", "trPrc": "0"}, {"basDt": "20250224", "idxNm": "\ucf54\uc2a4\ud53c 200 \ucee4\ubc84\ub4dc\ucf5c ATM \ub808\ubc84\ub9ac\uc9c0\uc9c0\uc218", "clpr": "1018.47", "vs": ".63", "fltRt": ".06", "mkp": "1024.2", "hipr": "1032.29", "lopr": "1008.82", "trqu": "0", "trPrc": "0"}, {"basDt": "20250224", "idxNm": "\ucf54\uc2a4\ud53c 200 \ucee4\ubc84\ub4dc\ucf5c ATM \uc9c0\uc218", "clpr": "1255.6", "vs": ".54", "fltRt": ".04", "mkp": "1259.13", "hipr": "1264.12", "lopr": "1249.65", "trqu": "0", "trPrc": "0"}, {"basDt": "20250224", "idxNm": "\ucf54\uc2a4\ud53c 200 \ud0c0\uac9f \uc704\ud074\ub9ac \ucee4\ubc84\ub4dc\ucf5c \uc9c0\uc218", "clpr": "1215.02", "vs": "-5.48", "fltRt": "-.45", "mkp": "1221.97", "hipr": "1221.97", "lopr": "1206.4", "trqu": "0", "trPrc": "0"}, {"basDt": "20250224", "idxNm": "\ucf54\uc2a4\ud53c 200 \ud504\ub85c\ud14d\ud2f0\ube0c\ud48b 5% OTM\uc9c0\uc218", "clpr": "168.82", "vs": "-.92", "fltRt": "-.54", "mkp": "169.87", "hipr": "169.88", "lopr": "167.7", "trqu": "0", "trPrc": "0"}, {"basDt": "20250224", "idxNm": "\ucf54\uc2a4\ud53c 200 \ud5ec\uc2a4\ucf00\uc5b4 TR", "clpr": "2313.42", "vs": "-12.43", "fltRt": "-.53", "mkp": "2325.26", "hipr": "2331.19", "lopr": "2300.07", "trqu": "0", "trPrc": "0"}, {"basDt": "20250224", "idxNm": "\ucf54\uc2a4\ud53c 200 \ud5ec\uc2a4\ucf00\uc5b4 \ub808\ubc84\ub9ac\uc9c0\uc9c0\uc218", "clpr": "809.48", "vs": "-8.94", "fltRt": "-1.09", "mkp": "817.81", "hipr": "821.98", "lopr": "800.08", "trqu": "0", "trPrc": "0"}, {"basDt": "20250224", "idxNm": "\ucf54\uc2a4\ud53c 200 \ud5ec\uc2a4\ucf00\uc5b4 \uc120\ubb3c\ub808\ubc84\ub9ac\uc9c0 \uc9c0\uc218", "clpr": "746.06", "vs": "-9.78", "fltRt": "-1.29", "mkp": "755.97", "hipr": "755.97", "lopr": "740.76", "trqu": "0", "trPrc": "0"}, {"basDt": "20250224", "idxNm": "\ucf54\uc2a4\ud53c 200 \ud5ec\uc2a4\ucf00\uc5b4 \uc120\ubb3c\uc778\ubc84\uc2a4 \uc9c0\uc218", "clpr": "594.89", "vs": "3.99", "fltRt": ".68", "mkp": "591.02", "hipr": "596.96", "lopr": "591.02", "trqu": "0", "trPrc": "0"}, {"basDt": "20250224", "idxNm": "\ucf54\uc2a4\ud53c 200 \ud5ec\uc2a4\ucf00\uc5b4 \uc120\ubb3c\uc778\ubc84\uc2a4-2X \uc9c0\uc218", "clpr": "166.52", "vs": "2.18", "fltRt": "1.33", "mkp": "164.37", "hipr": "167.67", "lopr": "164.37", "trqu": "0", "trPrc": "0"}, {"basDt": "20250224", "idxNm": "\ucf54\uc2a4\ud53c 200 \ud5ec\uc2a4\ucf00\uc5b4 \uc120\ubb3c\uc9c0\uc218", "clpr": "1088.38", "vs": "-7.18", "fltRt": "-.66", "mkp": "1095.56", "hipr": "1095.56", "lopr": "1084.54", "trqu": "0", "trPrc": "0"}, {"basDt": "20250224", "idxNm": "\ucf54\uc2a4\ud53c 200 \ud604\uc120\ubb3c \ub808\ubc84\ub9ac\uc9c01.5X\uc9c0\uc218", "clpr": "1879.61", "vs": "-20.1", "fltRt": "-1.06", "mkp": "1889.56", "hipr": "1890.64", "lopr": "1862.48", "trqu": "0", "trPrc": "0"}, {"basDt": "20250224", "idxNm": "\ucf54\uc2a4\ud53c 200 \ud604\uc120\ubb3c \ubaa9\ud45c\ubcc0\ub3d9\uc131 24% \uc9c0\uc218", "clpr": "1301.55", "vs": "-12.74", "fltRt": "-.97", "mkp": "1308.56", "hipr": "1309.17", "lopr": "1290.19", "trqu": "0", "trPrc": "0"}, {"basDt": "20250224", "idxNm": "\ucf54\uc2a4\ud53c 50 \ub3d9\uc77c\uac00\uc911\uc9c0\uc218", "clpr": "1912.88", "vs": "10.9", "fltRt": ".57", "mkp": "1892.36", "hipr": "1912.88", "lopr": "1892.3", "trqu": "81016986", "trPrc": "5099980155162"}, {"basDt": "20250224", "idxNm": "\ucf54\uc2a4\ud53c TR", "clpr": "3374.49", "vs": "-11.87", "fltRt": "-.35", "mkp": "3362.82", "hipr": "3374.49", "lopr": "3351.03", "trqu": "0", "trPrc": "0"}, {"basDt": "20250224", "idxNm": "\ucf54\uc2a4\ud53c USD \ud604\ubb3c \uc9c0\uc218", "clpr": "3358.06", "vs": "-28.79", "fltRt": "-.85", "mkp": "3360.9", "hipr": "3377.94", "lopr": "3340.4", "trqu": "0", "trPrc": "0"}, {"basDt": "20250224", "idxNm": "\ucf54\uc2a4\ud53c \uace0\ubc30\ub2f9 50 TR", "clpr": "5412.11", "vs": "15.44", "fltRt": ".29", "mkp": "5382.51", "hipr": "5412.11", "lopr": "5378.98", "trqu": "0", "trPrc": "0"}, {"basDt": "20250224", "idxNm": "\ucf54\uc2a4\ud53c \uace0\ubc30\ub2f9 \uc704\ud074\ub9ac \uace0\uc815 \ucee4\ubc84\ub4dc\ucf5c \uc9c0\uc218", "clpr": "1230.32", "vs": "4.33", "fltRt": ".35", "mkp": "1226.85", "hipr": "1230.41", "lopr": "1221.38", "trqu": "0", "trPrc": "0"}, {"basDt": "20250224", "idxNm": "\ucf54\uc2a4\ud53c \uace0\ubc30\ub2f9 \uc704\ud074\ub9ac \ucf5c\ub9e4\ub3c4 ATM \uc9c0\uc218", "clpr": "1658.31", "vs": "8.64", "fltRt": ".52", "mkp": "1653.53", "hipr": "1658.7", "lopr": "1646.16", "trqu": "0", "trPrc": "0"}, {"basDt": "20250224", "idxNm": "\ucf54\uc2a4\ud53c \ubc30\ub2f9\uc131\uc7a5 50 TR", "clpr": "5570.13", "vs": "33.03", "fltRt": ".6", "mkp": "5514.49", "hipr": "5570.13", "lopr": "5510.83", "trqu": "0", "trPrc": "0"}, {"basDt": "20250224", "idxNm": "\ucf54\uc2a4\ud53c200 10\ub144\uad6d\ucc44 \uc120\ubb3c\ud63c\ud569\uc9c0\uc218", "clpr": "1976.92", "vs": "-4.47", "fltRt": "-.23", "mkp": "1971.24", "hipr": "1981.21", "lopr": "1970.11", "trqu": "0", "trPrc": "0"}, {"basDt": "20250224", "idxNm": "\ucf54\uc2a4\ud53c200 \ub871 100% \ucf54\uc2a4\ub2e5150 \uc20f 100% \uc120\ubb3c\uc9c0\uc218", "clpr": "739.09", "vs": "-6.41", "fltRt": "-.86", "mkp": "747.63", "hipr": "749.58", "lopr": "737.95", "trqu": "0", "trPrc": "0"}, {"basDt": "20250224", "idxNm": "\ucf54\uc2a4\ud53c200 \ub871 100% \ucf54\uc2a4\ub2e5150 \uc20f 50% \uc120\ubb3c\uc9c0\uc218", "clpr": "1260.49", "vs": "-11.49", "fltRt": "-.9", "mkp": "1267.14", "hipr": "1269.17", "lopr": "1260.38", "trqu": "0", "trPrc": "0"}, {"basDt": "20250224", "idxNm": "\ucf54\uc2a4\ud53c200 \ucf54\uc2a4\ub2e5150 \uace0\uc815\ube44\uc911 3:7 \uc9c0\uc218", "clpr": "1468.17", "vs": "-.97", "fltRt": "-.07", "mkp": "1453.57", "hipr": "1468.49", "lopr": "1450.16", "trqu": "0", "trPrc": "0"}, {"basDt": "20250224", "idxNm": "\ucf54\uc2a4\ud53c200 \ucf54\uc2a4\ub2e5150 \uace0\uc815\ube44\uc911 5:5 \ub808\ubc84\ub9ac\uc9c0 \uc9c0\uc218", "clpr": "946.36", "vs": "-4.24", "fltRt": "-.45", "mkp": "931.26", "hipr": "946.36", "lopr": "926.01", "trqu": "0", "trPrc": "0"}, {"basDt": "20250224", "idxNm": "\ucf54\uc2a4\ud53c200 \ucf54\uc2a4\ub2e5150 \uace0\uc815\ube44\uc911 5:5 \uc9c0\uc218", "clpr": "1536.41", "vs": "-3.25", "fltRt": "-.21", "mkp": "1524.18", "hipr": "1536.41", "lopr": "1519.93", "trqu": "0", "trPrc": "0"}, {"basDt": "20250224", "idxNm": "\ucf54\uc2a4\ud53c200 \ucf54\uc2a4\ub2e5150 \uace0\uc815\ube44\uc911 7:3 \uc9c0\uc218", "clpr": "1573.78", "vs": "-5.63", "fltRt": "-.36", "mkp": "1564.39", "hipr": "1573.78", "lopr": "1559.21", "trqu": "0", "trPrc": "0"}]}}}}